{
    "rdapConformance": [
        "rdap_level_0",
        "cidr0",
        "arin_originas0"
    ],
    "notices": [
        {
            "title": "Terms of Service",
            "description": [
                "By using the ARIN RDAP/Whois service, you are agreeing to the RDAP/Whois Terms of Use"
            ],
            "links": [
                {
                    "value": "https://rdap.arin.net/registry/ip/103.253.96.39",
                    "rel": "about",
                    "type": "text/html",
                    "href": "https://www.arin.net/resources/registry/whois/tou/"
                }
            ]
        },
        {
            "title": "Whois Inaccuracy Reporting",
            "description": [
                "If you see inaccuracies in the results, please visit: "
            ],
            "links": [
                {
                    "value": "https://rdap.arin.net/registry/ip/103.253.96.39",
                    "rel": "about",
                    "type": "text/html",
                    "href": "https://www.arin.net/resources/registry/whois/inaccuracy_reporting/"
                }
            ]
        },
        {
            "title": "Copyright Notice",
            "description": [
                "Copyright 1997-2021, American Registry for Internet Numbers, Ltd."
            ]
        }
    ],
    "handle": "NET-103-253-96-0-1",
    "startAddress": "103.253.96.0",
    "endAddress": "103.253.99.255",
    "ipVersion": "v4",
    "name": "MT-226",
    "type": "DIRECT ALLOCATION",
    "parentHandle": "NET-103-0-0-0-1",
    "events": [
        {
            "eventAction": "last changed",
            "eventDate": "2017-03-29T17:21:06-04:00"
        },
        {
            "eventAction": "registration",
            "eventDate": "2017-03-29T17:21:03-04:00"
        }
    ],
    "links": [
        {
            "value": "https://rdap.arin.net/registry/ip/103.253.96.39",
            "rel": "self",
            "type": "application/rdap+json",
            "href": "https://rdap.arin.net/registry/ip/103.253.96.0"
        },
        {
            "value": "https://rdap.arin.net/registry/ip/103.253.96.39",
            "rel": "alternate",
            "type": "application/xml",
            "href": "https://whois.arin.net/rest/net/NET-103-253-96-0-1"
        }
    ],
    "entities": [
        {
            "handle": "MT-226",
            "vcardArray": [
                "vcard",
                [
                    [
                        "version",
                        {},
                        "text",
                        "4.0"
                    ],
                    [
                        "fn",
                        {},
                        "text",
                        "MAZAGAN TELECOM"
                    ],
                    [
                        "adr",
                        {
                            "label": "826 DECARIE ST\nMONTREAL\nQC\nH4L 3M9\nCanada"
                        },
                        "text",
                        [
                            "",
                            "",
                            "",
                            "",
                            "",
                            "",
                            ""
                        ]
                    ],
                    [
                        "kind",
                        {},
                        "text",
                        "org"
                    ]
                ]
            ],
            "roles": [
                "registrant"
            ],
            "links": [
                {
                    "value": "https://rdap.arin.net/registry/ip/103.253.96.39",
                    "rel": "self",
                    "type": "application/rdap+json",
                    "href": "https://rdap.arin.net/registry/entity/MT-226"
                },
                {
                    "value": "https://rdap.arin.net/registry/ip/103.253.96.39",
                    "rel": "alternate",
                    "type": "application/xml",
                    "href": "https://whois.arin.net/rest/org/MT-226"
                }
            ],
            "events": [
                {
                    "eventAction": "last changed",
                    "eventDate": "2017-01-28T08:32:29-05:00"
                },
                {
                    "eventAction": "registration",
                    "eventDate": "2013-10-01T09:41:37-04:00"
                }
            ],
            "entities": [
                {
                    "handle": "EKSE-ARIN",
                    "vcardArray": [
                        "vcard",
                        [
                            [
                                "version",
                                {},
                                "text",
                                "4.0"
                            ],
                            [
                                "adr",
                                {
                                    "label": "826 Decarie ST\nSaint Laurent\nQC\nH4L 3L9\nCanada"
                                },
                                "text",
                                [
                                    "",
                                    "",
                                    "",
                                    "",
                                    "",
                                    "",
                                    ""
                                ]
                            ],
                            [
                                "fn",
                                {},
                                "text",
                                "SALAH EDDINE EL KASBAOUI"
                            ],
                            [
                                "n",
                                {},
                                "text",
                                [
                                    "EL KASBAOUI",
                                    "SALAH EDDINE",
                                    "",
                                    "",
                                    ""
                                ]
                            ],
                            [
                                "kind",
                                {},
                                "text",
                                "individual"
                            ],
                            [
                                "email",
                                {},
                                "text",
                                "MAZAGANTELECOM@GMAIL.COM"
                            ],
                            [
                                "email",
                                {},
                                "text",
                                "Salaheddine@mazagantelecom.com"
                            ],
                            [
                                "email",
                                {},
                                "text",
                                "canadacanada675@gmail.com"
                            ],
                            [
                                "tel",
                                {
                                    "type": [
                                        "work",
                                        "voice"
                                    ]
                                },
                                "text",
                                "+1-514-591-3640"
                            ],
                            [
                                "tel",
                                {
                                    "type": [
                                        "work",
                                        "cell"
                                    ]
                                },
                                "text",
                                "+1-514-591-3640"
                            ]
                        ]
                    ],
                    "roles": [
                        "noc",
                        "administrative",
                        "technical",
                        "abuse"
                    ],
                    "links": [
                        {
                            "value": "https://rdap.arin.net/registry/ip/103.253.96.39",
                            "rel": "self",
                            "type": "application/rdap+json",
                            "href": "https://rdap.arin.net/registry/entity/EKSE-ARIN"
                        },
                        {
                            "value": "https://rdap.arin.net/registry/ip/103.253.96.39",
                            "rel": "alternate",
                            "type": "application/xml",
                            "href": "https://whois.arin.net/rest/poc/EKSE-ARIN"
                        }
                    ],
                    "events": [
                        {
                            "eventAction": "last changed",
                            "eventDate": "2020-01-31T10:37:27-05:00"
                        },
                        {
                            "eventAction": "registration",
                            "eventDate": "2013-09-16T12:26:59-04:00"
                        }
                    ],
                    "status": [
                        "validated"
                    ],
                    "port43": "whois.arin.net",
                    "objectClassName": "entity"
                }
            ],
            "port43": "whois.arin.net",
            "objectClassName": "entity"
        }
    ],
    "port43": "whois.arin.net",
    "status": [
        "active"
    ],
    "objectClassName": "ip network",
    "cidr0_cidrs": [
        {
            "v4prefix": "103.253.96.0",
            "length": 22
        }
    ],
    "arin_originas0_originautnums": []
}