{
    "handle": "130.159.0.0 - 130.159.255.255",
    "startAddress": "130.159.0.0",
    "endAddress": "130.159.255.255",
    "ipVersion": "v4",
    "name": "STRATH",
    "type": "LEGACY",
    "country": "GB",
    "parentHandle": "0.0.0.0 - 255.255.255.255",
    "entities": [
        {
            "handle": "HM1248-RIPE",
            "roles": [
                "technical"
            ],
            "objectClassName": "entity"
        },
        {
            "handle": "NM815-RIPE",
            "roles": [
                "administrative"
            ],
            "objectClassName": "entity"
        },
        {
            "handle": "ORG-STRA3-RIPE",
            "roles": [
                "registrant"
            ],
            "objectClassName": "entity"
        },
        {
            "handle": "UNISTRATH-MNT",
            "roles": [
                "registrant"
            ],
            "objectClassName": "entity"
        },
        {
            "handle": "ACRO11568-RIPE",
            "vcardArray": [
                "vcard",
                [
                    [
                        "version",
                        {},
                        "text",
                        "4.0"
                    ],
                    [
                        "fn",
                        {},
                        "text",
                        "University of Strathclyde Abuse contact"
                    ],
                    [
                        "kind",
                        {},
                        "text",
                        "group"
                    ],
                    [
                        "adr",
                        {
                            "label": "16, Richmond St\nGlasgow\nScotland\nGB\nG1 1XQ"
                        },
                        "text",
                        [
                            "",
                            "",
                            "",
                            "",
                            "",
                            "",
                            ""
                        ]
                    ],
                    [
                        "email",
                        {
                            "type": "email"
                        },
                        "text",
                        "csirt@strath.ac.uk"
                    ],
                    [
                        "email",
                        {
                            "type": "abuse"
                        },
                        "text",
                        "csirt@strath.ac.uk"
                    ],
                    [
                        "org",
                        {},
                        "text",
                        "ORG-STRA3-RIPE"
                    ]
                ]
            ],
            "roles": [
                "abuse"
            ],
            "entities": [
                {
                    "handle": "ORG-STRA3-RIPE",
                    "roles": [
                        "registrant"
                    ],
                    "objectClassName": "entity"
                },
                {
                    "handle": "UNISTRATH-MNT",
                    "roles": [
                        "registrant"
                    ],
                    "objectClassName": "entity"
                }
            ],
            "objectClassName": "entity"
        }
    ],
    "remarks": [
        {
            "description": [
                "University of Strathclyde"
            ]
        }
    ],
    "links": [
        {
            "value": "https://rdap.db.ripe.net/ip/130.159.52.86",
            "rel": "self",
            "href": "https://rdap.db.ripe.net/ip/130.159.52.86"
        },
        {
            "value": "http://www.ripe.net/data-tools/support/documentation/terms",
            "rel": "copyright",
            "href": "http://www.ripe.net/data-tools/support/documentation/terms"
        }
    ],
    "events": [
        {
            "eventAction": "last changed",
            "eventDate": "2019-12-04T13:09:06Z"
        }
    ],
    "rdapConformance": [
        "rdap_level_0"
    ],
    "notices": [
        {
            "title": "Filtered",
            "description": [
                "This output has been filtered."
            ]
        },
        {
            "title": "Source",
            "description": [
                "Objects returned came from source",
                "RIPE"
            ]
        },
        {
            "title": "Terms and Conditions",
            "description": [
                "This is the RIPE Database query service. The objects are in RDAP format."
            ],
            "links": [
                {
                    "value": "https://rdap.db.ripe.net/ip/130.159.52.86",
                    "rel": "terms-of-service",
                    "href": "http://www.ripe.net/db/support/db-terms-conditions.pdf",
                    "type": "application/pdf"
                }
            ]
        }
    ],
    "port43": "whois.ripe.net",
    "objectClassName": "ip network"
}