{
    "rdapConformance": [
        "rdap_level_0",
        "cidr0",
        "arin_originas0"
    ],
    "notices": [
        {
            "title": "Terms of Service",
            "description": [
                "By using the ARIN RDAP/Whois service, you are agreeing to the RDAP/Whois Terms of Use"
            ],
            "links": [
                {
                    "value": "https://rdap.arin.net/registry/ip/151.145.245.196",
                    "rel": "about",
                    "type": "text/html",
                    "href": "https://www.arin.net/resources/registry/whois/tou/"
                }
            ]
        },
        {
            "title": "Whois Inaccuracy Reporting",
            "description": [
                "If you see inaccuracies in the results, please visit: "
            ],
            "links": [
                {
                    "value": "https://rdap.arin.net/registry/ip/151.145.245.196",
                    "rel": "about",
                    "type": "text/html",
                    "href": "https://www.arin.net/resources/registry/whois/inaccuracy_reporting/"
                }
            ]
        },
        {
            "title": "Copyright Notice",
            "description": [
                "Copyright 1997-2021, American Registry for Internet Numbers, Ltd."
            ]
        }
    ],
    "handle": "NET-151-145-0-0-1",
    "startAddress": "151.145.0.0",
    "endAddress": "151.145.255.255",
    "ipVersion": "v4",
    "name": "BUSCH",
    "type": "DIRECT ASSIGNMENT",
    "parentHandle": "NET-151-0-0-0-0",
    "events": [
        {
            "eventAction": "last changed",
            "eventDate": "2012-04-02T10:31:36-04:00"
        },
        {
            "eventAction": "registration",
            "eventDate": "1991-06-11T00:00:00-04:00"
        }
    ],
    "links": [
        {
            "value": "https://rdap.arin.net/registry/ip/151.145.245.196",
            "rel": "self",
            "type": "application/rdap+json",
            "href": "https://rdap.arin.net/registry/ip/151.145.0.0"
        },
        {
            "value": "https://rdap.arin.net/registry/ip/151.145.245.196",
            "rel": "alternate",
            "type": "application/xml",
            "href": "https://whois.arin.net/rest/net/NET-151-145-0-0-1"
        }
    ],
    "entities": [
        {
            "handle": "ABC-2-Z",
            "vcardArray": [
                "vcard",
                [
                    [
                        "version",
                        {},
                        "text",
                        "4.0"
                    ],
                    [
                        "fn",
                        {},
                        "text",
                        "Anheuser Busch Companies, Inc."
                    ],
                    [
                        "adr",
                        {
                            "label": "One Busch Place 202-3\nSt.Louis\nMO\n63118\nUnited States"
                        },
                        "text",
                        [
                            "",
                            "",
                            "",
                            "",
                            "",
                            "",
                            ""
                        ]
                    ],
                    [
                        "kind",
                        {},
                        "text",
                        "org"
                    ]
                ]
            ],
            "roles": [
                "registrant"
            ],
            "links": [
                {
                    "value": "https://rdap.arin.net/registry/ip/151.145.245.196",
                    "rel": "self",
                    "type": "application/rdap+json",
                    "href": "https://rdap.arin.net/registry/entity/ABC-2-Z"
                },
                {
                    "value": "https://rdap.arin.net/registry/ip/151.145.245.196",
                    "rel": "alternate",
                    "type": "application/xml",
                    "href": "https://whois.arin.net/rest/org/ABC-2-Z"
                }
            ],
            "events": [
                {
                    "eventAction": "last changed",
                    "eventDate": "2011-09-24T08:30:57-04:00"
                },
                {
                    "eventAction": "registration",
                    "eventDate": "2008-04-04T14:07:37-04:00"
                }
            ],
            "entities": [
                {
                    "handle": "ZA104-ARIN",
                    "vcardArray": [
                        "vcard",
                        [
                            [
                                "version",
                                {},
                                "text",
                                "4.0"
                            ],
                            [
                                "adr",
                                {
                                    "label": "One Busch Place\nSt. Louis\nMO\n63118\nUnited States"
                                },
                                "text",
                                [
                                    "",
                                    "",
                                    "",
                                    "",
                                    "",
                                    "",
                                    ""
                                ]
                            ],
                            [
                                "fn",
                                {},
                                "text",
                                "Anheuser-Busch Companies"
                            ],
                            [
                                "org",
                                {},
                                "text",
                                "Anheuser-Busch Companies"
                            ],
                            [
                                "kind",
                                {},
                                "text",
                                "group"
                            ],
                            [
                                "email",
                                {},
                                "text",
                                "dl-dns@anheuser-busch.com"
                            ],
                            [
                                "tel",
                                {
                                    "type": [
                                        "work",
                                        "voice"
                                    ]
                                },
                                "text",
                                "+1-800-233-7825"
                            ]
                        ]
                    ],
                    "roles": [
                        "administrative",
                        "abuse",
                        "technical"
                    ],
                    "remarks": [
                        {
                            "title": "Unvalidated POC",
                            "description": [
                                "ARIN has attempted to validate the data for this POC, but has received no response from the POC since 2018-12-14"
                            ]
                        }
                    ],
                    "links": [
                        {
                            "value": "https://rdap.arin.net/registry/ip/151.145.245.196",
                            "rel": "self",
                            "type": "application/rdap+json",
                            "href": "https://rdap.arin.net/registry/entity/ZA104-ARIN"
                        },
                        {
                            "value": "https://rdap.arin.net/registry/ip/151.145.245.196",
                            "rel": "alternate",
                            "type": "application/xml",
                            "href": "https://whois.arin.net/rest/poc/ZA104-ARIN"
                        }
                    ],
                    "events": [
                        {
                            "eventAction": "last changed",
                            "eventDate": "2017-12-14T08:48:56-05:00"
                        },
                        {
                            "eventAction": "registration",
                            "eventDate": "2001-09-18T15:16:12-04:00"
                        }
                    ],
                    "port43": "whois.arin.net",
                    "objectClassName": "entity"
                }
            ],
            "port43": "whois.arin.net",
            "objectClassName": "entity"
        },
        {
            "handle": "ZA104-ARIN",
            "vcardArray": [
                "vcard",
                [
                    [
                        "version",
                        {},
                        "text",
                        "4.0"
                    ],
                    [
                        "adr",
                        {
                            "label": "One Busch Place\nSt. Louis\nMO\n63118\nUnited States"
                        },
                        "text",
                        [
                            "",
                            "",
                            "",
                            "",
                            "",
                            "",
                            ""
                        ]
                    ],
                    [
                        "fn",
                        {},
                        "text",
                        "Anheuser-Busch Companies"
                    ],
                    [
                        "org",
                        {},
                        "text",
                        "Anheuser-Busch Companies"
                    ],
                    [
                        "kind",
                        {},
                        "text",
                        "group"
                    ],
                    [
                        "email",
                        {},
                        "text",
                        "dl-dns@anheuser-busch.com"
                    ],
                    [
                        "tel",
                        {
                            "type": [
                                "work",
                                "voice"
                            ]
                        },
                        "text",
                        "+1-800-233-7825"
                    ]
                ]
            ],
            "roles": [
                "abuse",
                "technical"
            ],
            "remarks": [
                {
                    "title": "Unvalidated POC",
                    "description": [
                        "ARIN has attempted to validate the data for this POC, but has received no response from the POC since 2018-12-14"
                    ]
                }
            ],
            "links": [
                {
                    "value": "https://rdap.arin.net/registry/ip/151.145.245.196",
                    "rel": "self",
                    "type": "application/rdap+json",
                    "href": "https://rdap.arin.net/registry/entity/ZA104-ARIN"
                },
                {
                    "value": "https://rdap.arin.net/registry/ip/151.145.245.196",
                    "rel": "alternate",
                    "type": "application/xml",
                    "href": "https://whois.arin.net/rest/poc/ZA104-ARIN"
                }
            ],
            "events": [
                {
                    "eventAction": "last changed",
                    "eventDate": "2017-12-14T08:48:56-05:00"
                },
                {
                    "eventAction": "registration",
                    "eventDate": "2001-09-18T15:16:12-04:00"
                }
            ],
            "port43": "whois.arin.net",
            "objectClassName": "entity"
        }
    ],
    "port43": "whois.arin.net",
    "status": [
        "active"
    ],
    "objectClassName": "ip network",
    "cidr0_cidrs": [
        {
            "v4prefix": "151.145.0.0",
            "length": 16
        }
    ],
    "arin_originas0_originautnums": []
}