{
    "rdapConformance": [
        "rdap_level_0",
        "cidr0",
        "arin_originas0"
    ],
    "notices": [
        {
            "title": "Terms of Service",
            "description": [
                "By using the ARIN RDAP/Whois service, you are agreeing to the RDAP/Whois Terms of Use"
            ],
            "links": [
                {
                    "value": "https://rdap.arin.net/registry/ip/184.64.252.29",
                    "rel": "about",
                    "type": "text/html",
                    "href": "https://www.arin.net/resources/registry/whois/tou/"
                }
            ]
        },
        {
            "title": "Whois Inaccuracy Reporting",
            "description": [
                "If you see inaccuracies in the results, please visit: "
            ],
            "links": [
                {
                    "value": "https://rdap.arin.net/registry/ip/184.64.252.29",
                    "rel": "about",
                    "type": "text/html",
                    "href": "https://www.arin.net/resources/registry/whois/inaccuracy_reporting/"
                }
            ]
        },
        {
            "title": "Copyright Notice",
            "description": [
                "Copyright 1997-2021, American Registry for Internet Numbers, Ltd."
            ]
        }
    ],
    "handle": "NET-184-64-0-0-1",
    "startAddress": "184.64.0.0",
    "endAddress": "184.71.255.255",
    "ipVersion": "v4",
    "name": "SHAW-COMM",
    "type": "DIRECT ALLOCATION",
    "parentHandle": "NET-184-0-0-0-0",
    "events": [
        {
            "eventAction": "last changed",
            "eventDate": "2012-03-02T08:03:18-05:00"
        },
        {
            "eventAction": "registration",
            "eventDate": "2010-01-15T16:28:58-05:00"
        }
    ],
    "links": [
        {
            "value": "https://rdap.arin.net/registry/ip/184.64.252.29",
            "rel": "self",
            "type": "application/rdap+json",
            "href": "https://rdap.arin.net/registry/ip/184.64.0.0"
        },
        {
            "value": "https://rdap.arin.net/registry/ip/184.64.252.29",
            "rel": "alternate",
            "type": "application/xml",
            "href": "https://whois.arin.net/rest/net/NET-184-64-0-0-1"
        }
    ],
    "entities": [
        {
            "handle": "SHAWC",
            "vcardArray": [
                "vcard",
                [
                    [
                        "version",
                        {},
                        "text",
                        "4.0"
                    ],
                    [
                        "fn",
                        {},
                        "text",
                        "Shaw Communications Inc."
                    ],
                    [
                        "adr",
                        {
                            "label": "Suite 800\n630 - 3rd Ave. SW\nCalgary\nAB\nT2P-4L4\nCanada"
                        },
                        "text",
                        [
                            "",
                            "",
                            "",
                            "",
                            "",
                            "",
                            ""
                        ]
                    ],
                    [
                        "kind",
                        {},
                        "text",
                        "org"
                    ]
                ]
            ],
            "roles": [
                "registrant"
            ],
            "links": [
                {
                    "value": "https://rdap.arin.net/registry/ip/184.64.252.29",
                    "rel": "self",
                    "type": "application/rdap+json",
                    "href": "https://rdap.arin.net/registry/entity/SHAWC"
                },
                {
                    "value": "https://rdap.arin.net/registry/ip/184.64.252.29",
                    "rel": "alternate",
                    "type": "application/xml",
                    "href": "https://whois.arin.net/rest/org/SHAWC"
                }
            ],
            "events": [
                {
                    "eventAction": "last changed",
                    "eventDate": "2017-01-28T08:32:29-05:00"
                },
                {
                    "eventAction": "registration",
                    "eventDate": "2003-03-05T17:01:43-05:00"
                }
            ],
            "entities": [
                {
                    "handle": "ZS178-ARIN",
                    "vcardArray": [
                        "vcard",
                        [
                            [
                                "version",
                                {},
                                "text",
                                "4.0"
                            ],
                            [
                                "adr",
                                {
                                    "label": "630 3rd Avenue SW\r\nSuite 800\nCalgary\nAB\nT2P 4L4\nCanada"
                                },
                                "text",
                                [
                                    "",
                                    "",
                                    "",
                                    "",
                                    "",
                                    "",
                                    ""
                                ]
                            ],
                            [
                                "fn",
                                {},
                                "text",
                                "IP Admin"
                            ],
                            [
                                "org",
                                {},
                                "text",
                                "IP Admin"
                            ],
                            [
                                "kind",
                                {},
                                "text",
                                "group"
                            ],
                            [
                                "email",
                                {},
                                "text",
                                "ipadmin@sjrb.ca"
                            ],
                            [
                                "tel",
                                {
                                    "type": [
                                        "work",
                                        "voice"
                                    ]
                                },
                                "text",
                                "+1-403-750-7428"
                            ]
                        ]
                    ],
                    "roles": [
                        "administrative",
                        "technical"
                    ],
                    "links": [
                        {
                            "value": "https://rdap.arin.net/registry/ip/184.64.252.29",
                            "rel": "self",
                            "type": "application/rdap+json",
                            "href": "https://rdap.arin.net/registry/entity/ZS178-ARIN"
                        },
                        {
                            "value": "https://rdap.arin.net/registry/ip/184.64.252.29",
                            "rel": "alternate",
                            "type": "application/xml",
                            "href": "https://whois.arin.net/rest/poc/ZS178-ARIN"
                        }
                    ],
                    "events": [
                        {
                            "eventAction": "last changed",
                            "eventDate": "2021-01-05T12:29:02-05:00"
                        },
                        {
                            "eventAction": "registration",
                            "eventDate": "2001-12-17T09:59:46-05:00"
                        }
                    ],
                    "status": [
                        "validated"
                    ],
                    "port43": "whois.arin.net",
                    "objectClassName": "entity"
                },
                {
                    "handle": "SHAWA-ARIN",
                    "vcardArray": [
                        "vcard",
                        [
                            [
                                "version",
                                {},
                                "text",
                                "4.0"
                            ],
                            [
                                "adr",
                                {
                                    "label": "Suite 800,\n630 - 3rd Ave. SW\nCalgary\nAB\nT2P-4L4\nCanada"
                                },
                                "text",
                                [
                                    "",
                                    "",
                                    "",
                                    "",
                                    "",
                                    "",
                                    ""
                                ]
                            ],
                            [
                                "fn",
                                {},
                                "text",
                                "SHAW ABUSE"
                            ],
                            [
                                "org",
                                {},
                                "text",
                                "SHAW ABUSE"
                            ],
                            [
                                "kind",
                                {},
                                "text",
                                "group"
                            ],
                            [
                                "email",
                                {},
                                "text",
                                "internet.abuse@sjrb.ca"
                            ],
                            [
                                "tel",
                                {
                                    "type": [
                                        "work",
                                        "voice"
                                    ]
                                },
                                "text",
                                "+1-403-750-7420"
                            ]
                        ]
                    ],
                    "roles": [
                        "abuse"
                    ],
                    "remarks": [
                        {
                            "title": "Unvalidated POC",
                            "description": [
                                "ARIN has attempted to validate the data for this POC, but has received no response from the POC since 2019-02-07"
                            ]
                        }
                    ],
                    "links": [
                        {
                            "value": "https://rdap.arin.net/registry/ip/184.64.252.29",
                            "rel": "self",
                            "type": "application/rdap+json",
                            "href": "https://rdap.arin.net/registry/entity/SHAWA-ARIN"
                        },
                        {
                            "value": "https://rdap.arin.net/registry/ip/184.64.252.29",
                            "rel": "alternate",
                            "type": "application/xml",
                            "href": "https://whois.arin.net/rest/poc/SHAWA-ARIN"
                        }
                    ],
                    "events": [
                        {
                            "eventAction": "last changed",
                            "eventDate": "2018-02-07T10:00:53-05:00"
                        },
                        {
                            "eventAction": "registration",
                            "eventDate": "2003-03-04T11:30:13-05:00"
                        }
                    ],
                    "port43": "whois.arin.net",
                    "objectClassName": "entity"
                }
            ],
            "port43": "whois.arin.net",
            "objectClassName": "entity"
        },
        {
            "handle": "ZS178-ARIN",
            "vcardArray": [
                "vcard",
                [
                    [
                        "version",
                        {},
                        "text",
                        "4.0"
                    ],
                    [
                        "adr",
                        {
                            "label": "630 3rd Avenue SW\r\nSuite 800\nCalgary\nAB\nT2P 4L4\nCanada"
                        },
                        "text",
                        [
                            "",
                            "",
                            "",
                            "",
                            "",
                            "",
                            ""
                        ]
                    ],
                    [
                        "fn",
                        {},
                        "text",
                        "IP Admin"
                    ],
                    [
                        "org",
                        {},
                        "text",
                        "IP Admin"
                    ],
                    [
                        "kind",
                        {},
                        "text",
                        "group"
                    ],
                    [
                        "email",
                        {},
                        "text",
                        "ipadmin@sjrb.ca"
                    ],
                    [
                        "tel",
                        {
                            "type": [
                                "work",
                                "voice"
                            ]
                        },
                        "text",
                        "+1-403-750-7428"
                    ]
                ]
            ],
            "roles": [
                "technical"
            ],
            "links": [
                {
                    "value": "https://rdap.arin.net/registry/ip/184.64.252.29",
                    "rel": "self",
                    "type": "application/rdap+json",
                    "href": "https://rdap.arin.net/registry/entity/ZS178-ARIN"
                },
                {
                    "value": "https://rdap.arin.net/registry/ip/184.64.252.29",
                    "rel": "alternate",
                    "type": "application/xml",
                    "href": "https://whois.arin.net/rest/poc/ZS178-ARIN"
                }
            ],
            "events": [
                {
                    "eventAction": "last changed",
                    "eventDate": "2021-01-05T12:29:02-05:00"
                },
                {
                    "eventAction": "registration",
                    "eventDate": "2001-12-17T09:59:46-05:00"
                }
            ],
            "status": [
                "validated"
            ],
            "port43": "whois.arin.net",
            "objectClassName": "entity"
        }
    ],
    "port43": "whois.arin.net",
    "status": [
        "active"
    ],
    "objectClassName": "ip network",
    "cidr0_cidrs": [
        {
            "v4prefix": "184.64.0.0",
            "length": 13
        }
    ],
    "arin_originas0_originautnums": [
        6327
    ]
}