{
    "handle": "194.144.249.208 - 194.144.249.223",
    "startAddress": "194.144.249.208",
    "endAddress": "194.144.249.223",
    "ipVersion": "v4",
    "name": "IS-RUMFATALAGERINN",
    "type": "ASSIGNED PA",
    "country": "IS",
    "parentHandle": "194.144.0.0 - 194.144.255.255",
    "entities": [
        {
            "handle": "JHB2-RIPE",
            "roles": [
                "administrative"
            ],
            "objectClassName": "entity"
        },
        {
            "handle": "VFIS-NET-MNT",
            "roles": [
                "registrant"
            ],
            "objectClassName": "entity"
        },
        {
            "handle": "VFIS1-RIPE",
            "roles": [
                "technical"
            ],
            "objectClassName": "entity"
        },
        {
            "handle": "AR13790-RIPE",
            "vcardArray": [
                "vcard",
                [
                    [
                        "version",
                        {},
                        "text",
                        "4.0"
                    ],
                    [
                        "fn",
                        {},
                        "text",
                        "Abuse-C Role"
                    ],
                    [
                        "kind",
                        {},
                        "text",
                        "group"
                    ],
                    [
                        "adr",
                        {
                            "label": "Syn hf Sigurbjorn B. Larusson Sudurlandsbraut 8 108 Reykjavik ICELAND"
                        },
                        "text",
                        [
                            "",
                            "",
                            "",
                            "",
                            "",
                            "",
                            ""
                        ]
                    ],
                    [
                        "email",
                        {
                            "type": "email"
                        },
                        "text",
                        "transmission@vodafone.is"
                    ],
                    [
                        "email",
                        {
                            "type": "abuse"
                        },
                        "text",
                        "abuse@vodafone.is"
                    ]
                ]
            ],
            "roles": [
                "abuse"
            ],
            "entities": [
                {
                    "handle": "VFIS-NET-MNT",
                    "roles": [
                        "registrant"
                    ],
                    "objectClassName": "entity"
                }
            ],
            "objectClassName": "entity"
        }
    ],
    "remarks": [
        {
            "description": [
                "Rumfatalagerinn ehf.",
                "Blikastadavegi 2",
                "112 Reykjavik"
            ]
        }
    ],
    "links": [
        {
            "value": "https://rdap.db.ripe.net/ip/194.144.249.222",
            "rel": "self",
            "href": "https://rdap.db.ripe.net/ip/194.144.249.222"
        },
        {
            "value": "http://www.ripe.net/data-tools/support/documentation/terms",
            "rel": "copyright",
            "href": "http://www.ripe.net/data-tools/support/documentation/terms"
        }
    ],
    "events": [
        {
            "eventAction": "last changed",
            "eventDate": "2011-11-15T15:08:41Z"
        }
    ],
    "rdapConformance": [
        "rdap_level_0"
    ],
    "notices": [
        {
            "title": "Filtered",
            "description": [
                "This output has been filtered."
            ]
        },
        {
            "title": "Source",
            "description": [
                "Objects returned came from source",
                "RIPE"
            ]
        },
        {
            "title": "Terms and Conditions",
            "description": [
                "This is the RIPE Database query service. The objects are in RDAP format."
            ],
            "links": [
                {
                    "value": "https://rdap.db.ripe.net/ip/194.144.249.222",
                    "rel": "terms-of-service",
                    "href": "http://www.ripe.net/db/support/db-terms-conditions.pdf",
                    "type": "application/pdf"
                }
            ]
        }
    ],
    "port43": "whois.ripe.net",
    "objectClassName": "ip network"
}