{
    "rdapConformance": [
        "rdap_level_0",
        "cidr0",
        "arin_originas0"
    ],
    "notices": [
        {
            "title": "Terms of Service",
            "description": [
                "By using the ARIN RDAP/Whois service, you are agreeing to the RDAP/Whois Terms of Use"
            ],
            "links": [
                {
                    "value": "https://rdap.arin.net/registry/ip/208.82.78.30",
                    "rel": "about",
                    "type": "text/html",
                    "href": "https://www.arin.net/resources/registry/whois/tou/"
                }
            ]
        },
        {
            "title": "Whois Inaccuracy Reporting",
            "description": [
                "If you see inaccuracies in the results, please visit: "
            ],
            "links": [
                {
                    "value": "https://rdap.arin.net/registry/ip/208.82.78.30",
                    "rel": "about",
                    "type": "text/html",
                    "href": "https://www.arin.net/resources/registry/whois/inaccuracy_reporting/"
                }
            ]
        },
        {
            "title": "Copyright Notice",
            "description": [
                "Copyright 1997-2021, American Registry for Internet Numbers, Ltd."
            ]
        }
    ],
    "handle": "NET-208-82-76-0-1",
    "startAddress": "208.82.76.0",
    "endAddress": "208.82.79.255",
    "ipVersion": "v4",
    "name": "CITYOFMANCHESTERNH",
    "type": "DIRECT ASSIGNMENT",
    "parentHandle": "NET-208-0-0-0-0",
    "events": [
        {
            "eventAction": "last changed",
            "eventDate": "2012-03-02T08:03:18-05:00"
        },
        {
            "eventAction": "registration",
            "eventDate": "2007-09-13T17:40:55-04:00"
        }
    ],
    "links": [
        {
            "value": "https://rdap.arin.net/registry/ip/208.82.78.30",
            "rel": "self",
            "type": "application/rdap+json",
            "href": "https://rdap.arin.net/registry/ip/208.82.76.0"
        },
        {
            "value": "https://rdap.arin.net/registry/ip/208.82.78.30",
            "rel": "alternate",
            "type": "application/xml",
            "href": "https://whois.arin.net/rest/net/NET-208-82-76-0-1"
        }
    ],
    "entities": [
        {
            "handle": "CMN-13",
            "vcardArray": [
                "vcard",
                [
                    [
                        "version",
                        {},
                        "text",
                        "4.0"
                    ],
                    [
                        "fn",
                        {},
                        "text",
                        "City Of Manchester, NH"
                    ],
                    [
                        "adr",
                        {
                            "label": "ATTN: Information Systems Dept.\n100 Merrimack Street\nManchester\nNH\n03101\nUnited States"
                        },
                        "text",
                        [
                            "",
                            "",
                            "",
                            "",
                            "",
                            "",
                            ""
                        ]
                    ],
                    [
                        "kind",
                        {},
                        "text",
                        "org"
                    ]
                ]
            ],
            "roles": [
                "registrant"
            ],
            "links": [
                {
                    "value": "https://rdap.arin.net/registry/ip/208.82.78.30",
                    "rel": "self",
                    "type": "application/rdap+json",
                    "href": "https://rdap.arin.net/registry/entity/CMN-13"
                },
                {
                    "value": "https://rdap.arin.net/registry/ip/208.82.78.30",
                    "rel": "alternate",
                    "type": "application/xml",
                    "href": "https://whois.arin.net/rest/org/CMN-13"
                }
            ],
            "events": [
                {
                    "eventAction": "last changed",
                    "eventDate": "2011-09-24T08:30:57-04:00"
                },
                {
                    "eventAction": "registration",
                    "eventDate": "2006-06-28T14:35:44-04:00"
                }
            ],
            "entities": [
                {
                    "handle": "JFO64-ARIN",
                    "vcardArray": [
                        "vcard",
                        [
                            [
                                "version",
                                {},
                                "text",
                                "4.0"
                            ],
                            [
                                "adr",
                                {
                                    "label": "ATTN: Information Systems Dept.\n100 Merrimack Street\nManchester\nNH\n03101\nUnited States"
                                },
                                "text",
                                [
                                    "",
                                    "",
                                    "",
                                    "",
                                    "",
                                    "",
                                    ""
                                ]
                            ],
                            [
                                "fn",
                                {},
                                "text",
                                "Jean Fortier"
                            ],
                            [
                                "n",
                                {},
                                "text",
                                [
                                    "Fortier",
                                    "Jean",
                                    "",
                                    "",
                                    ""
                                ]
                            ],
                            [
                                "kind",
                                {},
                                "text",
                                "individual"
                            ],
                            [
                                "email",
                                {},
                                "text",
                                "jfortier@manchesternh.gov"
                            ],
                            [
                                "tel",
                                {
                                    "type": [
                                        "work",
                                        "voice"
                                    ]
                                },
                                "text",
                                "+1-603-624-6577;ext2320"
                            ]
                        ]
                    ],
                    "roles": [
                        "technical",
                        "abuse"
                    ],
                    "links": [
                        {
                            "value": "https://rdap.arin.net/registry/ip/208.82.78.30",
                            "rel": "self",
                            "type": "application/rdap+json",
                            "href": "https://rdap.arin.net/registry/entity/JFO64-ARIN"
                        },
                        {
                            "value": "https://rdap.arin.net/registry/ip/208.82.78.30",
                            "rel": "alternate",
                            "type": "application/xml",
                            "href": "https://whois.arin.net/rest/poc/JFO64-ARIN"
                        }
                    ],
                    "events": [
                        {
                            "eventAction": "last changed",
                            "eventDate": "2019-10-28T10:17:20-04:00"
                        },
                        {
                            "eventAction": "registration",
                            "eventDate": "2006-06-27T12:36:06-04:00"
                        }
                    ],
                    "status": [
                        "validated"
                    ],
                    "port43": "whois.arin.net",
                    "objectClassName": "entity"
                },
                {
                    "handle": "NOC2172-ARIN",
                    "vcardArray": [
                        "vcard",
                        [
                            [
                                "version",
                                {},
                                "text",
                                "4.0"
                            ],
                            [
                                "adr",
                                {
                                    "label": "ATTN: Information Systems Dept.\n100 Merrimack Street\nManchester\nNH\n03101\nUnited States"
                                },
                                "text",
                                [
                                    "",
                                    "",
                                    "",
                                    "",
                                    "",
                                    "",
                                    ""
                                ]
                            ],
                            [
                                "fn",
                                {},
                                "text",
                                "Network Operations Center"
                            ],
                            [
                                "org",
                                {},
                                "text",
                                "Network Operations Center"
                            ],
                            [
                                "kind",
                                {},
                                "text",
                                "group"
                            ],
                            [
                                "email",
                                {},
                                "text",
                                "MIS_OFFICE@manchesternh.gov"
                            ],
                            [
                                "tel",
                                {
                                    "type": [
                                        "work",
                                        "voice"
                                    ]
                                },
                                "text",
                                "+1-603-624-6577"
                            ]
                        ]
                    ],
                    "roles": [
                        "noc"
                    ],
                    "links": [
                        {
                            "value": "https://rdap.arin.net/registry/ip/208.82.78.30",
                            "rel": "self",
                            "type": "application/rdap+json",
                            "href": "https://rdap.arin.net/registry/entity/NOC2172-ARIN"
                        },
                        {
                            "value": "https://rdap.arin.net/registry/ip/208.82.78.30",
                            "rel": "alternate",
                            "type": "application/xml",
                            "href": "https://whois.arin.net/rest/poc/NOC2172-ARIN"
                        }
                    ],
                    "events": [
                        {
                            "eventAction": "last changed",
                            "eventDate": "2019-11-20T07:48:53-05:00"
                        },
                        {
                            "eventAction": "registration",
                            "eventDate": "2006-06-27T11:25:36-04:00"
                        }
                    ],
                    "status": [
                        "validated"
                    ],
                    "port43": "whois.arin.net",
                    "objectClassName": "entity"
                },
                {
                    "handle": "JMK41-ARIN",
                    "vcardArray": [
                        "vcard",
                        [
                            [
                                "version",
                                {},
                                "text",
                                "4.0"
                            ],
                            [
                                "adr",
                                {
                                    "label": "ATTN: Information Systems Dept.\n100 Merrimack Street\nManchester\nNH\n03101\nUnited States"
                                },
                                "text",
                                [
                                    "",
                                    "",
                                    "",
                                    "",
                                    "",
                                    "",
                                    ""
                                ]
                            ],
                            [
                                "fn",
                                {},
                                "text",
                                "Jacqueline Mary Keith"
                            ],
                            [
                                "n",
                                {},
                                "text",
                                [
                                    "Keith",
                                    "Jacqueline",
                                    "Mary",
                                    "",
                                    ""
                                ]
                            ],
                            [
                                "kind",
                                {},
                                "text",
                                "individual"
                            ],
                            [
                                "email",
                                {},
                                "text",
                                "elevesque@manchesternh.gov"
                            ],
                            [
                                "email",
                                {},
                                "text",
                                "mis@manchesternh.gov"
                            ],
                            [
                                "tel",
                                {
                                    "type": [
                                        "work",
                                        "voice"
                                    ]
                                },
                                "text",
                                "+1-603-624-6577"
                            ]
                        ]
                    ],
                    "roles": [
                        "administrative"
                    ],
                    "links": [
                        {
                            "value": "https://rdap.arin.net/registry/ip/208.82.78.30",
                            "rel": "self",
                            "type": "application/rdap+json",
                            "href": "https://rdap.arin.net/registry/entity/JMK41-ARIN"
                        },
                        {
                            "value": "https://rdap.arin.net/registry/ip/208.82.78.30",
                            "rel": "alternate",
                            "type": "application/xml",
                            "href": "https://whois.arin.net/rest/poc/JMK41-ARIN"
                        }
                    ],
                    "events": [
                        {
                            "eventAction": "last changed",
                            "eventDate": "2019-08-26T09:20:15-04:00"
                        },
                        {
                            "eventAction": "registration",
                            "eventDate": "2006-06-27T12:42:09-04:00"
                        }
                    ],
                    "status": [
                        "validated"
                    ],
                    "port43": "whois.arin.net",
                    "objectClassName": "entity"
                }
            ],
            "port43": "whois.arin.net",
            "objectClassName": "entity"
        },
        {
            "handle": "JFO64-ARIN",
            "vcardArray": [
                "vcard",
                [
                    [
                        "version",
                        {},
                        "text",
                        "4.0"
                    ],
                    [
                        "adr",
                        {
                            "label": "ATTN: Information Systems Dept.\n100 Merrimack Street\nManchester\nNH\n03101\nUnited States"
                        },
                        "text",
                        [
                            "",
                            "",
                            "",
                            "",
                            "",
                            "",
                            ""
                        ]
                    ],
                    [
                        "fn",
                        {},
                        "text",
                        "Jean Fortier"
                    ],
                    [
                        "n",
                        {},
                        "text",
                        [
                            "Fortier",
                            "Jean",
                            "",
                            "",
                            ""
                        ]
                    ],
                    [
                        "kind",
                        {},
                        "text",
                        "individual"
                    ],
                    [
                        "email",
                        {},
                        "text",
                        "jfortier@manchesternh.gov"
                    ],
                    [
                        "tel",
                        {
                            "type": [
                                "work",
                                "voice"
                            ]
                        },
                        "text",
                        "+1-603-624-6577;ext2320"
                    ]
                ]
            ],
            "roles": [
                "technical"
            ],
            "links": [
                {
                    "value": "https://rdap.arin.net/registry/ip/208.82.78.30",
                    "rel": "self",
                    "type": "application/rdap+json",
                    "href": "https://rdap.arin.net/registry/entity/JFO64-ARIN"
                },
                {
                    "value": "https://rdap.arin.net/registry/ip/208.82.78.30",
                    "rel": "alternate",
                    "type": "application/xml",
                    "href": "https://whois.arin.net/rest/poc/JFO64-ARIN"
                }
            ],
            "events": [
                {
                    "eventAction": "last changed",
                    "eventDate": "2019-10-28T10:17:20-04:00"
                },
                {
                    "eventAction": "registration",
                    "eventDate": "2006-06-27T12:36:06-04:00"
                }
            ],
            "status": [
                "validated"
            ],
            "port43": "whois.arin.net",
            "objectClassName": "entity"
        },
        {
            "handle": "NOC2172-ARIN",
            "vcardArray": [
                "vcard",
                [
                    [
                        "version",
                        {},
                        "text",
                        "4.0"
                    ],
                    [
                        "adr",
                        {
                            "label": "ATTN: Information Systems Dept.\n100 Merrimack Street\nManchester\nNH\n03101\nUnited States"
                        },
                        "text",
                        [
                            "",
                            "",
                            "",
                            "",
                            "",
                            "",
                            ""
                        ]
                    ],
                    [
                        "fn",
                        {},
                        "text",
                        "Network Operations Center"
                    ],
                    [
                        "org",
                        {},
                        "text",
                        "Network Operations Center"
                    ],
                    [
                        "kind",
                        {},
                        "text",
                        "group"
                    ],
                    [
                        "email",
                        {},
                        "text",
                        "MIS_OFFICE@manchesternh.gov"
                    ],
                    [
                        "tel",
                        {
                            "type": [
                                "work",
                                "voice"
                            ]
                        },
                        "text",
                        "+1-603-624-6577"
                    ]
                ]
            ],
            "roles": [
                "noc"
            ],
            "links": [
                {
                    "value": "https://rdap.arin.net/registry/ip/208.82.78.30",
                    "rel": "self",
                    "type": "application/rdap+json",
                    "href": "https://rdap.arin.net/registry/entity/NOC2172-ARIN"
                },
                {
                    "value": "https://rdap.arin.net/registry/ip/208.82.78.30",
                    "rel": "alternate",
                    "type": "application/xml",
                    "href": "https://whois.arin.net/rest/poc/NOC2172-ARIN"
                }
            ],
            "events": [
                {
                    "eventAction": "last changed",
                    "eventDate": "2019-11-20T07:48:53-05:00"
                },
                {
                    "eventAction": "registration",
                    "eventDate": "2006-06-27T11:25:36-04:00"
                }
            ],
            "status": [
                "validated"
            ],
            "port43": "whois.arin.net",
            "objectClassName": "entity"
        },
        {
            "handle": "JMK41-ARIN",
            "vcardArray": [
                "vcard",
                [
                    [
                        "version",
                        {},
                        "text",
                        "4.0"
                    ],
                    [
                        "adr",
                        {
                            "label": "ATTN: Information Systems Dept.\n100 Merrimack Street\nManchester\nNH\n03101\nUnited States"
                        },
                        "text",
                        [
                            "",
                            "",
                            "",
                            "",
                            "",
                            "",
                            ""
                        ]
                    ],
                    [
                        "fn",
                        {},
                        "text",
                        "Jacqueline Mary Keith"
                    ],
                    [
                        "n",
                        {},
                        "text",
                        [
                            "Keith",
                            "Jacqueline",
                            "Mary",
                            "",
                            ""
                        ]
                    ],
                    [
                        "kind",
                        {},
                        "text",
                        "individual"
                    ],
                    [
                        "email",
                        {},
                        "text",
                        "elevesque@manchesternh.gov"
                    ],
                    [
                        "email",
                        {},
                        "text",
                        "mis@manchesternh.gov"
                    ],
                    [
                        "tel",
                        {
                            "type": [
                                "work",
                                "voice"
                            ]
                        },
                        "text",
                        "+1-603-624-6577"
                    ]
                ]
            ],
            "roles": [
                "abuse"
            ],
            "links": [
                {
                    "value": "https://rdap.arin.net/registry/ip/208.82.78.30",
                    "rel": "self",
                    "type": "application/rdap+json",
                    "href": "https://rdap.arin.net/registry/entity/JMK41-ARIN"
                },
                {
                    "value": "https://rdap.arin.net/registry/ip/208.82.78.30",
                    "rel": "alternate",
                    "type": "application/xml",
                    "href": "https://whois.arin.net/rest/poc/JMK41-ARIN"
                }
            ],
            "events": [
                {
                    "eventAction": "last changed",
                    "eventDate": "2019-08-26T09:20:15-04:00"
                },
                {
                    "eventAction": "registration",
                    "eventDate": "2006-06-27T12:42:09-04:00"
                }
            ],
            "status": [
                "validated"
            ],
            "port43": "whois.arin.net",
            "objectClassName": "entity"
        }
    ],
    "port43": "whois.arin.net",
    "status": [
        "active"
    ],
    "objectClassName": "ip network",
    "cidr0_cidrs": [
        {
            "v4prefix": "208.82.76.0",
            "length": 22
        }
    ],
    "arin_originas0_originautnums": [
        19101
    ]
}