{
    "rdapConformance": [
        "rdap_level_0",
        "cidr0",
        "arin_originas0"
    ],
    "notices": [
        {
            "title": "Terms of Service",
            "description": [
                "By using the ARIN RDAP/Whois service, you are agreeing to the RDAP/Whois Terms of Use"
            ],
            "links": [
                {
                    "value": "https://rdap.arin.net/registry/ip/50.83.20.63",
                    "rel": "about",
                    "type": "text/html",
                    "href": "https://www.arin.net/resources/registry/whois/tou/"
                }
            ]
        },
        {
            "title": "Whois Inaccuracy Reporting",
            "description": [
                "If you see inaccuracies in the results, please visit: "
            ],
            "links": [
                {
                    "value": "https://rdap.arin.net/registry/ip/50.83.20.63",
                    "rel": "about",
                    "type": "text/html",
                    "href": "https://www.arin.net/resources/registry/whois/inaccuracy_reporting/"
                }
            ]
        },
        {
            "title": "Copyright Notice",
            "description": [
                "Copyright 1997-2021, American Registry for Internet Numbers, Ltd."
            ]
        }
    ],
    "handle": "NET-50-80-0-0-1",
    "startAddress": "50.80.0.0",
    "endAddress": "50.83.255.255",
    "ipVersion": "v4",
    "name": "MEDIACOM-RESIDENTIAL-CUST",
    "type": "DIRECT ALLOCATION",
    "parentHandle": "NET-50-0-0-0-0",
    "events": [
        {
            "eventAction": "last changed",
            "eventDate": "2012-02-24T09:44:34-05:00"
        },
        {
            "eventAction": "registration",
            "eventDate": "2010-11-03T17:09:03-04:00"
        }
    ],
    "links": [
        {
            "value": "https://rdap.arin.net/registry/ip/50.83.20.63",
            "rel": "self",
            "type": "application/rdap+json",
            "href": "https://rdap.arin.net/registry/ip/50.80.0.0"
        },
        {
            "value": "https://rdap.arin.net/registry/ip/50.83.20.63",
            "rel": "alternate",
            "type": "application/xml",
            "href": "https://whois.arin.net/rest/net/NET-50-80-0-0-1"
        }
    ],
    "entities": [
        {
            "handle": "MCC-244",
            "vcardArray": [
                "vcard",
                [
                    [
                        "version",
                        {},
                        "text",
                        "4.0"
                    ],
                    [
                        "fn",
                        {},
                        "text",
                        "Mediacom Communications Corp"
                    ],
                    [
                        "adr",
                        {
                            "label": "1 Mediacom Way\nMediacom Park\nNY\n10918\nUnited States"
                        },
                        "text",
                        [
                            "",
                            "",
                            "",
                            "",
                            "",
                            "",
                            ""
                        ]
                    ],
                    [
                        "kind",
                        {},
                        "text",
                        "org"
                    ]
                ]
            ],
            "roles": [
                "registrant"
            ],
            "remarks": [
                {
                    "title": "Registration Comments",
                    "description": [
                        "For abuse issues contact abuse@mediacomcc.com"
                    ]
                }
            ],
            "links": [
                {
                    "value": "https://rdap.arin.net/registry/ip/50.83.20.63",
                    "rel": "self",
                    "type": "application/rdap+json",
                    "href": "https://rdap.arin.net/registry/entity/MCC-244"
                },
                {
                    "value": "https://rdap.arin.net/registry/ip/50.83.20.63",
                    "rel": "alternate",
                    "type": "application/xml",
                    "href": "https://whois.arin.net/rest/org/MCC-244"
                }
            ],
            "events": [
                {
                    "eventAction": "last changed",
                    "eventDate": "2018-08-29T08:33:24-04:00"
                },
                {
                    "eventAction": "registration",
                    "eventDate": "2008-02-05T14:05:33-05:00"
                }
            ],
            "entities": [
                {
                    "handle": "NAH5-ARIN",
                    "vcardArray": [
                        "vcard",
                        [
                            [
                                "version",
                                {},
                                "text",
                                "4.0"
                            ],
                            [
                                "adr",
                                {
                                    "label": "1 Mediacom Way\nMediacom Park\nNY\n10918\nUnited States"
                                },
                                "text",
                                [
                                    "",
                                    "",
                                    "",
                                    "",
                                    "",
                                    "",
                                    ""
                                ]
                            ],
                            [
                                "fn",
                                {},
                                "text",
                                "Nisar Ahmad"
                            ],
                            [
                                "n",
                                {},
                                "text",
                                [
                                    "Ahmad",
                                    "Nisar",
                                    "",
                                    "",
                                    ""
                                ]
                            ],
                            [
                                "kind",
                                {},
                                "text",
                                "individual"
                            ],
                            [
                                "email",
                                {},
                                "text",
                                "nahmad@mediacomcc.com"
                            ],
                            [
                                "tel",
                                {
                                    "type": [
                                        "work",
                                        "voice"
                                    ]
                                },
                                "text",
                                "+1-845-443-2698"
                            ],
                            [
                                "tel",
                                {
                                    "type": [
                                        "work",
                                        "cell"
                                    ]
                                },
                                "text",
                                "+1-845-313-4002"
                            ]
                        ]
                    ],
                    "roles": [
                        "technical"
                    ],
                    "remarks": [
                        {
                            "title": "Unvalidated POC",
                            "description": [
                                "ARIN has attempted to validate the data for this POC, but has received no response from the POC since 2020-07-21"
                            ]
                        }
                    ],
                    "links": [
                        {
                            "value": "https://rdap.arin.net/registry/ip/50.83.20.63",
                            "rel": "self",
                            "type": "application/rdap+json",
                            "href": "https://rdap.arin.net/registry/entity/NAH5-ARIN"
                        },
                        {
                            "value": "https://rdap.arin.net/registry/ip/50.83.20.63",
                            "rel": "alternate",
                            "type": "application/xml",
                            "href": "https://whois.arin.net/rest/poc/NAH5-ARIN"
                        }
                    ],
                    "events": [
                        {
                            "eventAction": "last changed",
                            "eventDate": "2019-07-22T15:05:55-04:00"
                        },
                        {
                            "eventAction": "registration",
                            "eventDate": "2010-07-23T14:00:49-04:00"
                        }
                    ],
                    "port43": "whois.arin.net",
                    "objectClassName": "entity"
                },
                {
                    "handle": "HCD1-ARIN",
                    "vcardArray": [
                        "vcard",
                        [
                            [
                                "version",
                                {},
                                "text",
                                "4.0"
                            ],
                            [
                                "adr",
                                {
                                    "label": "2195 Ingersoll Ave\nDes Moines\nIA\n50312\nUnited States"
                                },
                                "text",
                                [
                                    "",
                                    "",
                                    "",
                                    "",
                                    "",
                                    "",
                                    ""
                                ]
                            ],
                            [
                                "fn",
                                {},
                                "text",
                                "Henry Clay Dean"
                            ],
                            [
                                "n",
                                {},
                                "text",
                                [
                                    "Dean",
                                    "Henry",
                                    "Clay",
                                    "",
                                    ""
                                ]
                            ],
                            [
                                "kind",
                                {},
                                "text",
                                "individual"
                            ],
                            [
                                "email",
                                {},
                                "text",
                                "hdean@mediacomcc.com"
                            ],
                            [
                                "tel",
                                {
                                    "type": [
                                        "work",
                                        "voice"
                                    ]
                                },
                                "text",
                                "+1-515-559-0223"
                            ]
                        ]
                    ],
                    "roles": [
                        "technical"
                    ],
                    "links": [
                        {
                            "value": "https://rdap.arin.net/registry/ip/50.83.20.63",
                            "rel": "self",
                            "type": "application/rdap+json",
                            "href": "https://rdap.arin.net/registry/entity/HCD1-ARIN"
                        },
                        {
                            "value": "https://rdap.arin.net/registry/ip/50.83.20.63",
                            "rel": "alternate",
                            "type": "application/xml",
                            "href": "https://whois.arin.net/rest/poc/HCD1-ARIN"
                        }
                    ],
                    "events": [
                        {
                            "eventAction": "last changed",
                            "eventDate": "2021-01-26T07:51:16-05:00"
                        },
                        {
                            "eventAction": "registration",
                            "eventDate": "2012-01-25T11:17:46-05:00"
                        }
                    ],
                    "status": [
                        "validated"
                    ],
                    "port43": "whois.arin.net",
                    "objectClassName": "entity"
                },
                {
                    "handle": "JWA248-ARIN",
                    "vcardArray": [
                        "vcard",
                        [
                            [
                                "version",
                                {},
                                "text",
                                "4.0"
                            ],
                            [
                                "adr",
                                {
                                    "label": "100 Crystal Run Road\nMiddletown\nNY\n10941\nUnited States"
                                },
                                "text",
                                [
                                    "",
                                    "",
                                    "",
                                    "",
                                    "",
                                    "",
                                    ""
                                ]
                            ],
                            [
                                "fn",
                                {},
                                "text",
                                "JR Walden"
                            ],
                            [
                                "n",
                                {},
                                "text",
                                [
                                    "Walden",
                                    "JR",
                                    "",
                                    "",
                                    ""
                                ]
                            ],
                            [
                                "kind",
                                {},
                                "text",
                                "individual"
                            ],
                            [
                                "email",
                                {},
                                "text",
                                "jrwalden@mediacomcc.com"
                            ],
                            [
                                "tel",
                                {
                                    "type": [
                                        "work",
                                        "voice"
                                    ]
                                },
                                "text",
                                "+1-845-695-2680"
                            ]
                        ]
                    ],
                    "roles": [
                        "administrative"
                    ],
                    "remarks": [
                        {
                            "title": "Unvalidated POC",
                            "description": [
                                "ARIN has attempted to validate the data for this POC, but has received no response from the POC since 2010-09-29"
                            ]
                        }
                    ],
                    "links": [
                        {
                            "value": "https://rdap.arin.net/registry/ip/50.83.20.63",
                            "rel": "self",
                            "type": "application/rdap+json",
                            "href": "https://rdap.arin.net/registry/entity/JWA248-ARIN"
                        },
                        {
                            "value": "https://rdap.arin.net/registry/ip/50.83.20.63",
                            "rel": "alternate",
                            "type": "application/xml",
                            "href": "https://whois.arin.net/rest/poc/JWA248-ARIN"
                        }
                    ],
                    "events": [
                        {
                            "eventAction": "last changed",
                            "eventDate": "2009-09-27T09:00:34-04:00"
                        },
                        {
                            "eventAction": "registration",
                            "eventDate": "2008-02-25T14:07:32-05:00"
                        }
                    ],
                    "port43": "whois.arin.net",
                    "objectClassName": "entity"
                },
                {
                    "handle": "MEDIA2-ARIN",
                    "vcardArray": [
                        "vcard",
                        [
                            [
                                "version",
                                {},
                                "text",
                                "4.0"
                            ],
                            [
                                "adr",
                                {
                                    "label": "100 Crystal Run Road\nMiddletown\nNY\n10941\nUnited States"
                                },
                                "text",
                                [
                                    "",
                                    "",
                                    "",
                                    "",
                                    "",
                                    "",
                                    ""
                                ]
                            ],
                            [
                                "fn",
                                {},
                                "text",
                                "Mediacom Abuse"
                            ],
                            [
                                "org",
                                {},
                                "text",
                                "Mediacom Abuse"
                            ],
                            [
                                "kind",
                                {},
                                "text",
                                "group"
                            ],
                            [
                                "email",
                                {},
                                "text",
                                "abuse@mediacombb.net"
                            ],
                            [
                                "tel",
                                {
                                    "type": [
                                        "work",
                                        "voice"
                                    ]
                                },
                                "text",
                                "+1-845-695-2600;ext2600"
                            ]
                        ]
                    ],
                    "roles": [
                        "abuse"
                    ],
                    "remarks": [
                        {
                            "title": "Unvalidated POC",
                            "description": [
                                "ARIN has attempted to validate the data for this POC, but has received no response from the POC since 2011-08-06"
                            ]
                        }
                    ],
                    "links": [
                        {
                            "value": "https://rdap.arin.net/registry/ip/50.83.20.63",
                            "rel": "self",
                            "type": "application/rdap+json",
                            "href": "https://rdap.arin.net/registry/entity/MEDIA2-ARIN"
                        },
                        {
                            "value": "https://rdap.arin.net/registry/ip/50.83.20.63",
                            "rel": "alternate",
                            "type": "application/xml",
                            "href": "https://whois.arin.net/rest/poc/MEDIA2-ARIN"
                        }
                    ],
                    "events": [
                        {
                            "eventAction": "last changed",
                            "eventDate": "2010-08-06T07:36:26-04:00"
                        },
                        {
                            "eventAction": "registration",
                            "eventDate": "2009-01-16T11:00:40-05:00"
                        }
                    ],
                    "port43": "whois.arin.net",
                    "objectClassName": "entity"
                }
            ],
            "port43": "whois.arin.net",
            "objectClassName": "entity"
        }
    ],
    "port43": "whois.arin.net",
    "status": [
        "active"
    ],
    "objectClassName": "ip network",
    "cidr0_cidrs": [
        {
            "v4prefix": "50.80.0.0",
            "length": 14
        }
    ],
    "arin_originas0_originautnums": []
}